{
    "Ar36": {
        "error": 0.0003565197229802203,
        "error_type": "",
        "fit": "previous",
        "references": [
            {
                "exclude": false,
                "record_id": "ba-01-A-32499"
            }
        ],
        "value": 0.02354159640559136
    },
    "Ar37": {
        "error": 0.010187509869305915,
        "error_type": "",
        "fit": "previous",
        "references": [
            {
                "exclude": false,
                "record_id": "ba-01-A-32499"
            }
        ],
        "value": 0.013964475217925846
    },
    "Ar38": {
        "error": 0.010388399267129752,
        "error_type": "",
        "fit": "previous",
        "references": [
            {
                "exclude": false,
                "record_id": "ba-01-A-32499"
            }
        ],
        "value": 0.008858340872405428
    },
    "Ar39": {
        "error": 0.009637162673921625,
        "error_type": "",
        "fit": "previous",
        "references": [
            {
                "exclude": false,
                "record_id": "ba-01-A-32499"
            }
        ],
        "value": 0.006480535625343835
    },
    "Ar40": {
        "error": 0.022559896936231203,
        "error_type": "",
        "fit": "previous",
        "references": [
            {
                "exclude": false,
                "record_id": "ba-01-A-32499"
            }
        ],
        "value": 6.769753203892145
    }
}