{
    "Ar36": {
        "error": 0.00024658026722548603,
        "error_type": "",
        "fit": "previous",
        "references": [
            {
                "exclude": false,
                "record_id": "ba-01-A-32617"
            }
        ],
        "value": 0.01585397879050304
    },
    "Ar37": {
        "error": 0.010283485847928773,
        "error_type": "",
        "fit": "previous",
        "references": [
            {
                "exclude": false,
                "record_id": "ba-01-A-32617"
            }
        ],
        "value": 0.0205813223762911
    },
    "Ar38": {
        "error": 0.008648955166891674,
        "error_type": "",
        "fit": "previous",
        "references": [
            {
                "exclude": false,
                "record_id": "ba-01-A-32617"
            }
        ],
        "value": 0.005551879228128406
    },
    "Ar39": {
        "error": 0.008364950624365862,
        "error_type": "",
        "fit": "previous",
        "references": [
            {
                "exclude": false,
                "record_id": "ba-01-A-32617"
            }
        ],
        "value": 0.01747333899732015
    },
    "Ar40": {
        "error": 0.02278173112371807,
        "error_type": "",
        "fit": "previous",
        "references": [
            {
                "exclude": false,
                "record_id": "ba-01-A-32617"
            }
        ],
        "value": 4.4782507053673895
    }
}